mdvtools/__init__.py
mdvtools/chart_prototypes.py
mdvtools/charts/abundance_box_plot.py
mdvtools/charts/base_plot.py
mdvtools/charts/box_plot.py
mdvtools/charts/density_scatter_plot.py
mdvtools/charts/dot_plot.py
mdvtools/charts/heatmap_plot.py
mdvtools/charts/histogram_plot.py
mdvtools/charts/multi_line_plot.py
mdvtools/charts/pie_chart.py
mdvtools/charts/ring_chart.py
mdvtools/charts/row_chart.py
mdvtools/charts/row_summary_box_plot.py
mdvtools/charts/sankey_plot.py
mdvtools/charts/scatter_plot.py
mdvtools/charts/scatter_plot_3D.py
mdvtools/charts/selection_dialog_plot.py
mdvtools/charts/stacked_row_plot.py
mdvtools/charts/table_plot.py
mdvtools/charts/text_box_plot.py
mdvtools/charts/view.py
mdvtools/charts/violin_plot.py
mdvtools/charts/wordcloud_plot.py
mdvtools/cli.py
mdvtools/conversions.py
mdvtools/image_view_prototype.py
mdvtools/logging_config.py
mdvtools/mdvproject.py
mdvtools/server_utils.py
mdvtools/serverlite.py
mdvtools/static/10M_points.js
mdvtools/static/10Mand1_points.js
mdvtools/static/basic_example.js
mdvtools/static/basic_filtering.js
mdvtools/static/index.html
mdvtools/static/netlify.toml
mdvtools/static/assets/Button-Bk9omZah.js
mdvtools/static/assets/Button-Bk9omZah.js.map
mdvtools/static/assets/ImportProjectDialog-BBNfJo0k.js
mdvtools/static/assets/ImportProjectDialog-BBNfJo0k.js.map
mdvtools/static/assets/MarkdownText-BYcNYvoZ.js
mdvtools/static/assets/MarkdownText-BYcNYvoZ.js.map
mdvtools/static/assets/ThemeProvider-CAZk5-N1.js
mdvtools/static/assets/ThemeProvider-CAZk5-N1.js.map
mdvtools/static/assets/VivViewerMDV-D_q-5ccV.js
mdvtools/static/assets/VivViewerMDV-D_q-5ccV.js.map
mdvtools/static/assets/binWorker-DIC2QqPk.js
mdvtools/static/assets/binWorker-DIC2QqPk.js.map
mdvtools/static/assets/boxPlotWorker-BvOiGWqU.js
mdvtools/static/assets/boxPlotWorker-BvOiGWqU.js.map
mdvtools/static/assets/catColWorker-BRK20MZB.js
mdvtools/static/assets/catColWorker-BRK20MZB.js.map
mdvtools/static/assets/catWorker-D5lhlpxE.js
mdvtools-1.1.dist-info/METADATA
mdvtools-1.1.dist-info/WHEEL
mdvtools-1.1.dist-info/entry_points.txt
mdvtools-1.1.dist-info/RECORD
