Metadata-Version: 2.4
Name: mdvtools
Version: 1.1
Summary: Multi Dimensional Viewer (MDV) is web based application for analyzing data
Project-URL: Homepage, https://github.com/Taylor-CCB-Group/MDV
Project-URL: Bug Tracker, https://github.com/Taylor-CCB-Group/MDV/issues
Author-email: Martin Sergeant <m.j.sergeant1@googlemail.com>, PeterTodd <peter.todd@well.ox.ac.uk>
License-Expression: GPL-3.0-only
Classifier: License :: OSI Approved :: GNU General Public License v3 (GPLv3)
Classifier: Operating System :: OS Independent
Classifier: Programming Language :: Python :: 3
Requires-Python: >=3.10
Requires-Dist: anndata!=0.10.9,>=0.10.8
Requires-Dist: fasteners==0.19
Requires-Dist: flask>=2.2.0
Requires-Dist: h5py>=3.5.0
Requires-Dist: mudata>=0.2.3
Requires-Dist: numpy>=1.22
Requires-Dist: pandas>=1.5.0
Requires-Dist: pyyaml>=5.3
Requires-Dist: scanpy>=1.7.2
Requires-Dist: scipy>=1.7.3
Requires-Dist: typing-extensions>=4.1.0
Requires-Dist: werkzeug>=2.3.0
